indykite_sdk/__init__.py
indykite_sdk/api.py
indykite_sdk/example.py
indykite_sdk/config/__init__.py
indykite_sdk/config/app_space.py
indykite_sdk/config/application.py
indykite_sdk/config/application_agent.py
indykite_sdk/config/application_agent_credential.py
indykite_sdk/config/config_node.py
indykite_sdk/config/customer.py
indykite_sdk/config/helper.py
indykite_sdk/config/oauth2_application.py
indykite_sdk/config/oauth2_provider.py
indykite_sdk/config/service_account.py
indykite_sdk/config/service_account_credential.py
indykite_sdk/config/tenant.py
indykite_sdk/identity/__init__.py
indykite_sdk/identity/change_password.py
indykite_sdk/identity/delete.py
indykite_sdk/identity/enrich_token.py
indykite_sdk/identity/get_digital_twin.py
indykite_sdk/identity/helper.py
indykite_sdk/identity/introspect_token.py
indykite_sdk/identity/patch_properties.py
indykite_sdk/identity/verification.py
indykite_sdk/indykite/__init__.py
indykite_sdk/indykite/config/__init__.py
indykite_sdk/indykite/config/v1beta1/__init__.py
indykite_sdk/indykite/config/v1beta1/config_management_api_pb2.py
indykite_sdk/indykite/config/v1beta1/config_management_api_pb2_grpc.py
indykite_sdk/indykite/config/v1beta1/model_pb2.py
indykite_sdk/indykite/config/v1beta1/model_pb2_grpc.py
indykite_sdk/indykite/events/__init__.py
indykite_sdk/indykite/events/v1beta1/__init__.py
indykite_sdk/indykite/events/v1beta1/events_pb2.py
indykite_sdk/indykite/events/v1beta1/events_pb2_grpc.py
indykite_sdk/indykite/identity/__init__.py
indykite_sdk/indykite/identity/v1beta1/__init__.py
indykite_sdk/indykite/identity/v1beta1/attributes_pb2.py
indykite_sdk/indykite/identity/v1beta1/attributes_pb2_grpc.py
indykite_sdk/indykite/identity/v1beta1/authenteq_pb2.py
indykite_sdk/indykite/identity/v1beta1/authenteq_pb2_grpc.py
indykite_sdk/indykite/identity/v1beta1/document_pb2.py
indykite_sdk/indykite/identity/v1beta1/document_pb2_grpc.py
indykite_sdk/indykite/identity/v1beta1/identity_management_api_pb2.py
jarvis_sdk_python-1.5.0.dist-info/LICENSE
jarvis_sdk_python-1.5.0.dist-info/METADATA
jarvis_sdk_python-1.5.0.dist-info/WHEEL
jarvis_sdk_python-1.5.0.dist-info/top_level.txt
jarvis_sdk_python-1.5.0.dist-info/RECORD
