Metadata-Version: 2.1
Name: jarvis-sdk-python
Version: 1.5.0
Summary: A python SDK package for Indykite's jarvis system (with protobuf)
Home-page: https://github.com/indykite/jarvis-sdk-python
Author: Indykite
Author-email: test@indykite.com
License: Apache-2.0
Classifier: Programming Language :: Python :: 3
Classifier: License :: OSI Approved :: Apache Software License
Classifier: Operating System :: OS Independent
Requires-Python: ~=3.8
License-File: LICENSE
Requires-Dist: authlib
Requires-Dist: certifi
Requires-Dist: grpcio
Requires-Dist: google-api-python-client
Requires-Dist: google-cloud-storage
Requires-Dist: protobuf
